pewhits/__init__.py
pewhits/__main__.py
pewhits/models.py
pewhits_client_sdk-0.9.0.dist-info/METADATA
pewhits_client_sdk-0.9.0.dist-info/WHEEL
pewhits_client_sdk-0.9.0.dist-info/top_level.txt
pewhits_client_sdk-0.9.0.dist-info/RECORD
