Metadata-Version: 2.4
Name: pewhits-client-sdk
Version: 0.9.0
Summary: A Python client SDK for the PewHits radio server
Author-email: Chitransh Shrivastava <chitransh819@gmail.com>
License: MIT
Requires-Python: >=3.11
Requires-Dist: typing_extensions>=4.12.2
Requires-Dist: cattrs>=22.2.0
Requires-Dist: quattro>=22.2.0
Requires-Dist: attrs>=24.2.0
Requires-Dist: aiohttp>=3.10.5
